LICENSE
MANIFEST.in
README.rst
gorun.py
requirements.txt
setup.py
gorun.egg-info/PKG-INFO
gorun.egg-info/SOURCES.txt
gorun.egg-info/dependency_links.txt
gorun.egg-info/not-zip-safe
gorun.egg-info/requires.txt
gorun.egg-info/top_level.txt