Metadata-Version: 1.0
Name: gorun
Version: 1.7
Summary: Wrapper on pyinotify for running commands (often tests)
Home-page: http://github.com/peterbe/python-gorun
Author: Peter Bengtsson
Author-email: mail@peterb.com
License: BSD
Platform: UNKNOWN
Classifier: Programming Language :: Python :: 2
Classifier: Intended Audience :: Developers
Classifier: Operating System :: POSIX :: Linux
Classifier: Topic :: Software Development :: Testing
Classifier: Topic :: Software Development :: Build Tools
